eeggan/__init__.py
eeggan/__main__.py
eeggan/autoencoder_training_main.py
eeggan/gan_training_main.py
eeggan/generate_samples_main.py
eeggan/get_gan_config.py
eeggan/setup_tutorial_main.py
eeggan/vae_training_main.py
eeggan/visualize_main.py
eeggan/auxiliary/checkpoint_to_csv.py
eeggan/auxiliary/create_averaged_erps.py
eeggan/auxiliary/data_downsampling.py
eeggan/data/eeggan_training_example.csv
eeggan/data/eeggan_validation_example.csv
eeggan/helpers/dataloader.py
eeggan/helpers/ddp_training.py
eeggan/helpers/get_master.py
eeggan/helpers/initialize_gan.py
eeggan/helpers/system_inputs.py
eeggan/helpers/trainer.py
eeggan/helpers/visualize_pca.py
eeggan/helpers/visualize_spectogram.py
eeggan/nn_architecture/ae_networks.py
eeggan/nn_architecture/losses.py
eeggan/nn_architecture/models.py
eeggan/nn_architecture/tts_gan_components.py
eeggan/nn_architecture/vae_networks.py
eeggan/tests/test_ae_training.py
eeggan/tests/test_functionality.py
eeggan/tests/test_gan_training.py
eeggan/tests/test_generate_samples.py
eeggan/tests/test_multi-electrode.py
eeggan/tests/test_synthetic.py
eeggan/tests/test_visualization.py
eeggan/trained_ae/pretrained_autoencoder.pt
eeggan/trained_models/pretrained_gan.pt
eeggan-2.0.2.dist-info/METADATA
eeggan-2.0.2.dist-info/WHEEL
eeggan-2.0.2.dist-info/entry_points.txt
eeggan-2.0.2.dist-info/licenses/LICENSE.md
eeggan-2.0.2.dist-info/RECORD
