Metadata-Version: 2.4
Name: eeggan
Version: 2.0.2
Summary: This package uses Generative Adversarial Networks (GANs) to augment EEG data to enhance classification performance.
Project-URL: Homepage, https://musslick.github.io/AER_website/Research.html
Project-URL: Repository, https://github.com/AutoResearch/EEG-GAN
Project-URL: Documentation, https://autoresearch.github.io/EEG-GAN/
Author-email: Autonomous Empirical Research Group <sebastian_musslick@brown.edu>
License-File: LICENSE.md
Requires-Python: >=3.7
Requires-Dist: einops<0.5,>=0.4
Requires-Dist: matplotlib<4.0,>=3.5
Requires-Dist: numpy<2.0,>=1.24
Requires-Dist: pandas<2.3,>=2.2
Requires-Dist: scikit-learn<2.0,>=1.1
Requires-Dist: scipy<2.0,>=1.8
Requires-Dist: torch<2.4,>=2.3
Requires-Dist: torchaudio<2.4,>=2.3
Requires-Dist: torchsummary<1.6,>=1.5
Requires-Dist: torchvision<0.19,>=0.18
Requires-Dist: tqdm<5.0,>=4.66
